parquetranger/__init__.py
parquetranger/core.py
parquetranger/ingestor.py
parquetranger/tests/__init__.py
parquetranger/tests/test_core.py
parquetranger/tests/test_diff_cols.py
parquetranger/tests/test_envs.py
parquetranger/tests/test_ingestors.py
parquetranger/tests/test_init.py
parquetranger/tests/test_metadata.py
parquetranger/tests/test_parallel.py
parquetranger/tests/test_writer.py
parquetranger-0.6.0.dist-info/LICENSE
parquetranger-0.6.0.dist-info/WHEEL
parquetranger-0.6.0.dist-info/METADATA
parquetranger-0.6.0.dist-info/RECORD
