Metadata-Version: 2.1
Name: parquetranger
Version: 0.6.0
Summary: Read and write parquet files
Author-email: Endre Márk Borza <endremborza@gmail.com>
Requires-Python: >=3.10
Requires-Dist: pandas>=2.0.1
Requires-Dist: pyarrow
Requires-Dist: atqo>=0.2.2
Requires-Dist: branthebuilder[doc] ; extra == "doc"
Requires-Dist: branthebuilder ; extra == "test"
Requires-Dist: faker ; extra == "test"
Project-URL: Homepage, https://github.com/endremborza/parquetranger
Provides-Extra: doc
Provides-Extra: test
